ds/__init__.py
ds/bot.py
ds/inter.py
ds/labeler.py
ds/error/token.py
ds/type/message.py
discord_user_bots-1.0.dist-info/METADATA
discord_user_bots-1.0.dist-info/WHEEL
discord_user_bots-1.0.dist-info/top_level.txt
discord_user_bots-1.0.dist-info/RECORD
