Metadata-Version: 2.1
Name: discord-user-bots
Version: 1.0
Home-page: https://github.com/CCCProo/discord_user_bot
Author: Ваше Имя
Classifier: Programming Language :: Python :: 3
Classifier: License :: OSI Approved :: MIT License
Classifier: Operating System :: OS Independent
Requires-Dist: pydantic
Requires-Dist: requests
Requires-Dist: aiohttp
Requires-Dist: cachetools
Requires-Dist: pyclean
